scrapper/__init__.py
scrapper/scrapper.py
dynamicscrapper-10.0.7.dist-info/METADATA
dynamicscrapper-10.0.7.dist-info/WHEEL
dynamicscrapper-10.0.7.dist-info/top_level.txt
dynamicscrapper-10.0.7.dist-info/RECORD
